ABlooper/ABlooper.py
ABlooper/__init__.py
ABlooper/command_line.py
ABlooper/models.py
ABlooper/openmm_refine.py
ABlooper/rosetta_refine.py
ABlooper/utils.py
ABlooper/trained_model/final_model
ABlooper/trained_model/final_model_imgt
ABlooper-1.1.2.dist-info/LICENSE
ABlooper-1.1.2.dist-info/METADATA
ABlooper-1.1.2.dist-info/WHEEL
ABlooper-1.1.2.dist-info/entry_points.txt
ABlooper-1.1.2.dist-info/top_level.txt
ABlooper-1.1.2.dist-info/RECORD
