Metadata-Version: 2.1
Name: ABlooper
Version: 1.1.2
Summary: Set of functions to predict CDR structure
Maintainer: Brennan Abanades
Maintainer-email: brennan.abanadeskenyon@stx.ox.ac.uk
License: BSD 3-clause license
License-File: LICENSE
Requires-Dist: numpy
Requires-Dist: einops (>=0.3)
Requires-Dist: torch (>=1.6)
